dnstap_receiver/__init__.py
dnstap_receiver/api_server.py
dnstap_receiver/dnstap.conf
dnstap_receiver/receiver.py
dnstap_receiver/statistics.py
dnstap_receiver/dns/__init__.py
dnstap_receiver/dns/parser.py
dnstap_receiver/dns/rcode.py
dnstap_receiver/dns/rdatatype.py
dnstap_receiver/inputs/__init__.py
dnstap_receiver/inputs/dnstap_decoder.py
dnstap_receiver/inputs/input_sniffer.py
dnstap_receiver/inputs/input_socket.py
dnstap_receiver/inputs/input_tcpclient.py
dnstap_receiver/outputs/__init__.py
dnstap_receiver/outputs/output_dnstap.py
dnstap_receiver/outputs/output_elasticsearch.py
dnstap_receiver/outputs/output_file.py
dnstap_receiver/outputs/output_kafka.py
dnstap_receiver/outputs/output_metrics.py
dnstap_receiver/outputs/output_pgsql.py
dnstap_receiver/outputs/output_pgsql_userfunc.py
dnstap_receiver/outputs/output_rabbitmq.py
dnstap_receiver/outputs/output_stdout.py
dnstap_receiver/outputs/output_syslog.py
dnstap_receiver/outputs/output_tcp.py
dnstap_receiver/outputs/transform.py
dnstap_receiver-4.7.0.dist-info/LICENSE
dnstap_receiver-4.7.0.dist-info/METADATA
dnstap_receiver-4.7.0.dist-info/WHEEL
dnstap_receiver-4.7.0.dist-info/entry_points.txt
dnstap_receiver-4.7.0.dist-info/top_level.txt
dnstap_receiver-4.7.0.dist-info/RECORD
