Metadata-Version: 2.1
Name: dnstap-receiver
Version: 4.7.0
Summary: Python Dnstap receiver
Home-page: https://github.com/dmachard/dnstap_receiver
Author: Denis MACHARD
Author-email: d.machard@gmail.com
Keywords: dnstap receiver client json yaml text
Platform: any
Classifier: License :: OSI Approved :: MIT License
Classifier: Programming Language :: Python :: 3
Classifier: Operating System :: OS Independent
Classifier: Topic :: Software Development :: Libraries
License-File: LICENSE
Requires-Dist: dnstap-pb
Requires-Dist: pyyaml
Requires-Dist: aiohttp
Requires-Dist: geoip2
Requires-Dist: tlds
Requires-Dist: cachetools
Requires-Dist: fstrm
Requires-Dist: requests
Provides-Extra: kafka
Requires-Dist: confluent-kafka ; extra == 'kafka'
Provides-Extra: pgsql
Requires-Dist: asyncpg ; extra == 'pgsql'
Provides-Extra: rabbitmq
Requires-Dist: pika ; extra == 'rabbitmq'
